LICENSE
MANIFEST.in
README.md
pyproject.toml
requirements.txt
setup.py
rointe_sdk.egg-info/PKG-INFO
rointe_sdk.egg-info/SOURCES.txt
rointe_sdk.egg-info/dependency_links.txt
rointe_sdk.egg-info/requires.txt
rointe_sdk.egg-info/top_level.txt
rointesdk/__init__.py
rointesdk/device.py
rointesdk/dto.py
rointesdk/model.py
rointesdk/rointe_api.py
rointesdk/settings.py
rointesdk/utils.py