Metadata-Version: 2.2
Name: rointe-sdk
Version: 1.6.0
Summary: Python SDK for rointeconnect.com
Home-page: https://github.com/tggm/rointe-sdk
Author: tggm
License: MIT
License-File: LICENSE
Requires-Dist: requests>=2.27.1
Requires-Dist: packaging>=21.2
Dynamic: author
Dynamic: description
Dynamic: description-content-type
Dynamic: home-page
Dynamic: license
Dynamic: requires-dist
Dynamic: summary
